MANIFEST.in
README.rst
bash-completion.sh
requirements.txt
setup.py
playlabs/README.rst
playlabs/init.sh
playlabs/init.yml
playlabs/package.yml
playlabs/project.yml
playlabs/role-all.yml
playlabs/role.yml
playlabs.egg-info/PKG-INFO
playlabs.egg-info/SOURCES.txt
playlabs.egg-info/dependency_links.txt
playlabs.egg-info/entry_points.txt
playlabs.egg-info/requires.txt
playlabs.egg-info/top_level.txt
playlabs/callback_plugins/failer.py
playlabs/cli/__init__.py
playlabs/cli/ansible.py
playlabs/cli/clicmd.py
playlabs/cli/exception.py
playlabs/cli/help.txt
playlabs/cli/main.py
playlabs/cli/parser.py
playlabs/cli/ssh.py
playlabs/cli/tools.py
playlabs/filter_plugins/playlabs_filters.py
playlabs/inventory_template/README.rst
playlabs/inventory_template/inventory.yaml
playlabs/inventory_template/group_vars/all/backup_password.yml
playlabs/inventory_template/group_vars/all/letsencrypt.yml
playlabs/inventory_template/group_vars/all/project.yml
playlabs/inventory_template/group_vars/all/users.yml
playlabs/plugins/django/backup.post.sh
playlabs/plugins/django/backup.pre.sh
playlabs/plugins/django/deploy.post.yml
playlabs/plugins/django/deploy.pre.yml
playlabs/plugins/django/restore.post.sh
playlabs/plugins/django/restore.pre.sh
playlabs/plugins/django/vars.yml
playlabs/plugins/postgres/backup.post.sh
playlabs/plugins/postgres/backup.pre.sh
playlabs/plugins/postgres/deploy.post.yml
playlabs/plugins/postgres/deploy.pre.yml
playlabs/plugins/postgres/restore.post.sh
playlabs/plugins/postgres/restore.pre.sh
playlabs/plugins/postgres/vars.yml
playlabs/plugins/sentry/backup.post.sh
playlabs/plugins/sentry/backup.pre.sh
playlabs/plugins/sentry/deploy.post.yml
playlabs/plugins/sentry/deploy.pre.yml
playlabs/plugins/sentry/restore.post.sh
playlabs/plugins/sentry/restore.pre.sh
playlabs/plugins/sentry/vars.yml
playlabs/plugins/uwsgi/backup.post.sh
playlabs/plugins/uwsgi/backup.pre.sh
playlabs/plugins/uwsgi/deploy.post.yml
playlabs/plugins/uwsgi/deploy.pre.yml
playlabs/plugins/uwsgi/restore.post.sh
playlabs/plugins/uwsgi/restore.pre.sh
playlabs/plugins/uwsgi/vars.yml
playlabs/roles/backup/handlers/main.yml
playlabs/roles/backup/tasks/main.yml
